txl_local_kernels/__init__.py
txl_local_kernels/connect.py
txl_local_kernels/driver.py
txl_local_kernels/kernelspec.py
txl_local_kernels/main.py
txl_local_kernels/message.py
txl_local_kernels/paths.py
txl_local_kernels-0.3.6.dist-info/METADATA
txl_local_kernels-0.3.6.dist-info/WHEEL
txl_local_kernels-0.3.6.dist-info/entry_points.txt
txl_local_kernels-0.3.6.dist-info/licenses/LICENSE.txt
txl_local_kernels-0.3.6.dist-info/RECORD
